setup.cfg
setup.py
MSApi/Assortment.py
MSApi/Attribute.py
MSApi/AttributeInfo.py
MSApi/Bundle.py
MSApi/CompanySettings.py
MSApi/Counterparty.py
MSApi/Currency.py
MSApi/CustomEntity.py
MSApi/CustomTemplate.py
MSApi/Discount.py
MSApi/DiscountHandler.py
MSApi/Employee.py
MSApi/Group.py
MSApi/MSApi.py
MSApi/MSLowApi.py
MSApi/Meta.py
MSApi/ObjectMS.py
MSApi/Organization.py
MSApi/PriceType.py
MSApi/Product.py
MSApi/ProductFolder.py
MSApi/Project.py
MSApi/SalesChannel.py
MSApi/Service.py
MSApi/State.py
MSApi/Store.py
MSApi/SubObjectMS.py
MSApi/Task.py
MSApi/Template.py
MSApi/Variant.py
MSApi/Webhook.py
MSApi/__init__.py
MSApi/exceptions.py
MSApi/mixins.py
MSApi/properties.py
MSApi.egg-info/PKG-INFO
MSApi.egg-info/SOURCES.txt
MSApi.egg-info/dependency_links.txt
MSApi.egg-info/not-zip-safe
MSApi.egg-info/requires.txt
MSApi.egg-info/top_level.txt
MSApi/documents/CashIn.py
MSApi/documents/CashOut.py
MSApi/documents/CustomerOrder.py
MSApi/documents/Demand.py
MSApi/documents/DocumentMS.py
MSApi/documents/Processing.py
MSApi/documents/ProcessingOrder.py
MSApi/documents/ProcessingPlan.py
MSApi/documents/__init__.py
MSApi/mixin/AccountIdMixin.py
MSApi/mixin/AgentMixin.py
MSApi/mixin/ArchivedMixin.py
MSApi/mixin/AttributeMixin.py
MSApi/mixin/CreateNewMixin.py
MSApi/mixin/DescriptionMixin.py
MSApi/mixin/GenCustomTemplatesMixin.py
MSApi/mixin/GenListMixin.py
MSApi/mixin/GroupMixin.py
MSApi/mixin/IsSharedMixin.py
MSApi/mixin/NameMixin.py
MSApi/mixin/ProductfolderMixin.py
MSApi/mixin/RequestByIdMixin.py
MSApi/mixin/RequestLabelMixin.py
MSApi/mixin/SalePricesMixin.py
MSApi/mixin/StateMixin.py
MSApi/mixin/__init__.py
MSApi/properties/DateTimeFilter.py
MSApi/properties/Expand.py
MSApi/properties/Filter.py
MSApi/properties/Order.py
MSApi/properties/Search.py
MSApi/properties/__init__.py