Metadata-Version: 2.1
Name: MSApi
Version: 0.2.10
Summary: Python API for manage MoySklad
Home-page: UNKNOWN
Author-email: serheos@gmail.com
License: UNKNOWN
Platform: UNKNOWN
